{
    "micro": {
        "title": "Microcontroller Programming"
    },
    "engineering ": {
        "title": "Software Engineering"
    },
    "docker": {
        "title": "Docker"
    },
    "javascript": {
        "title": "JavaScript / TypeScript"
    },
    "php": {
        "title": "PHP",
        "offSite": [
            {
                "url": "https://stackoverflow.com/questions/75815394/can-doctrine-hydrate-my-entity-with-a-custom-scalar-values-e-g-aggregate-case/75815481#75815481",
                "title": "Hydrating a Doctrine entity with a custom scalar values"
            },
            {
                "url": "https://stackoverflow.com/questions/15761685/multiple-dynamic-database-connections-in-symfony2/30800216#30800216",
                "title": "Multiple, dynamic database connections in Symfony 2"
            },
            {
                "url": "https://stackoverflow.com/questions/53408755/symfony-production-mode-error-reports-and-post-values",
                "title": "Symfony Production Mode Error Reports and POST values"
            },
            {
                "url": "https://stackoverflow.com/questions/60930236/symfony-3-console-exception-logging-only-displayed-on-console",
                "title": "Symfony 3 Console exception logging"
            }
        ]
    },
    "shell": {
        "title": "Shell Miscellany"
    },
    "diary": {
        "title": "The Diary of an Aged Hacker"
    },
    "philosophy": {
        "title": "\"Philosophy\""
    }
}
